{
  "editor:follow-link": [
    {
      "modifiers": [
        "Mod"
      ],
      "key": "Enter"
    }
  ],
  "editor:open-link-in-new-leaf": [
    {
      "modifiers": [
        "Mod",
        "Shift"
      ],
      "key": "Enter"
    }
  ],
  "app:go-forward": [
    {
      "modifiers": [
        "Mod",
        "Shift"
      ],
      "key": "I"
    }
  ],
  "app:go-back": [
    {
      "modifiers": [
        "Mod",
        "Shift"
      ],
      "key": "O"
    }
  ],
  "editor:open-link-in-new-window": [],
  "editor:open-link-in-new-split": [
    {
      "modifiers": [
        "Mod",
        "Shift"
      ],
      "key": "R"
    }
  ],
  "editor:toggle-code": [
    {
      "modifiers": [
        "Mod"
      ],
      "key": "J"
    }
  ],
  "editor:toggle-highlight": [
    {
      "modifiers": [
        "Mod"
      ],
      "key": "K"
    }
  ],
  "editor:insert-link": [],
  "editor:focus-right": [
    {
      "modifiers": [
        "Ctrl",
        "Mod"
      ],
      "key": "R"
    }
  ],
  "editor:focus-left": [
    {
      "modifiers": [
        "Ctrl",
        "Mod"
      ],
      "key": "L"
    }
  ],
  "obsidian-footnotes:insert-named-footnote": [
    {
      "modifiers": [
        "Alt"
      ],
      "key": "M"
    }
  ],
  "darlal-switcher-plus:switcher-plus:open-symbols-active": [
    {
      "modifiers": [
        "Ctrl",
        "Mod"
      ],
      "key": "F"
    }
  ],
  "app:toggle-left-sidebar": [
    {
      "modifiers": [
        "Alt"
      ],
      "key": "Backspace"
    }
  ],
  "app:toggle-right-sidebar": [
    {
      "modifiers": [
        "Mod"
      ],
      "key": "Backspace"
    }
  ],
  "editor:swap-line-up": [
    {
      "modifiers": [
        "Mod",
        "Shift"
      ],
      "key": "ArrowUp"
    }
  ],
  "editor:swap-line-down": [
    {
      "modifiers": [
        "Mod",
        "Shift"
      ],
      "key": "ArrowDown"
    }
  ]
}