{
  "main": {
    "id": "3e3a18a1570987e5",
    "type": "split",
    "children": [
      {
        "id": "b36d62511fd80fb3",
        "type": "tabs",
        "children": [
          {
            "id": "701603769442cda3",
            "type": "leaf",
            "state": {
              "type": "empty",
              "state": {}
            }
          }
        ]
      }
    ],
    "direction": "vertical"
  },
  "left": {
    "id": "5aa7b23f2d215440",
    "type": "mobile-drawer",
    "children": [
      {
        "id": "4fd7a5ae58837a18",
        "type": "leaf",
        "state": {
          "type": "file-explorer",
          "state": {
            "sortOrder": "alphabetical"
          }
        }
      },
      {
        "id": "17d546f38cadc174",
        "type": "leaf",
        "state": {
          "type": "search",
          "state": {
            "query": "",
            "matchingCase": false,
            "explainSearch": false,
            "collapseAll": false,
            "extraContext": false,
            "sortOrder": "alphabetical"
          }
        }
      },
      {
        "id": "5d56ef95c147f066",
        "type": "leaf",
        "state": {
          "type": "tag",
          "state": {
            "sortOrder": "frequency",
            "useHierarchy": true
          }
        }
      },
      {
        "id": "3a9e56e8d9165574",
        "type": "leaf",
        "state": {
          "type": "bookmarks",
          "state": {}
        }
      }
    ],
    "currentTab": 0
  },
  "right": {
    "id": "31f4124598417097",
    "type": "mobile-drawer",
    "children": [
      {
        "id": "e46b04225b76250d",
        "type": "leaf",
        "state": {
          "type": "backlink",
          "state": {
            "collapseAll": false,
            "extraContext": false,
            "sortOrder": "alphabetical",
            "showSearch": false,
            "searchQuery": "",
            "backlinkCollapsed": false,
            "unlinkedCollapsed": true
          }
        }
      },
      {
        "id": "b9ffbeb241d25bf6",
        "type": "leaf",
        "state": {
          "type": "outgoing-link",
          "state": {
            "linksCollapsed": false,
            "unlinkedCollapsed": true
          }
        }
      },
      {
        "id": "e1658b2328dab0e3",
        "type": "leaf",
        "state": {
          "type": "outline",
          "state": {}
        }
      }
    ],
    "currentTab": 0
  },
  "left-ribbon": {
    "hiddenItems": {
      "switcher:Open quick switcher": false,
      "graph:Open graph view": false,
      "canvas:Create new canvas": false,
      "daily-notes:Open today's daily note": false,
      "templates:Insert template": false,
      "command-palette:Open command palette": false
    }
  },
  "active": "701603769442cda3",
  "lastOpenFiles": []
}